django_advanced_search/__init__.py
django_advanced_search/mixins.py
django_advanced_search/tokens.py
django_advanced_search-1.0.0.dist-info/LICENSE
django_advanced_search-1.0.0.dist-info/METADATA
django_advanced_search-1.0.0.dist-info/WHEEL
django_advanced_search-1.0.0.dist-info/top_level.txt
django_advanced_search-1.0.0.dist-info/RECORD
