Metadata-Version: 2.1
Name: django-advanced-search
Version: 1.0.0
Summary: Django admin mixin for advanced search inspired by sentry, github and discord search
Home-page: https://github.com/sandbox-pokhara/django-advanced-search.git
Author: Pradish Bijukchhe
Author-email: pradishbijukchhe@gmail.com
Classifier: Environment :: Web Environment
Classifier: Framework :: Django
Classifier: Intended Audience :: Developers
Classifier: License :: OSI Approved :: MIT License
Classifier: Operating System :: OS Independent
Classifier: Programming Language :: Python
Classifier: Programming Language :: Python :: 3
Classifier: Programming Language :: Python :: 3 :: Only
Classifier: Topic :: Internet :: WWW/HTTP
Classifier: Topic :: Internet :: WWW/HTTP :: Dynamic Content
Requires-Python: >=3
License-File: LICENSE
Requires-Dist: Django
